LICENSE
MANIFEST.in
README.md
setup.py
pis/__init__.py
pis/config.json
pis/config.py
pis/lib.py
pis/main.py
pis/test_all.py
pis.egg-info/PKG-INFO
pis.egg-info/SOURCES.txt
pis.egg-info/dependency_links.txt
pis.egg-info/entry_points.txt
pis.egg-info/top_level.txt