Metadata-Version: 1.1
Name: pis
Version: 0.3.0
Summary: Install python package as cloned repo from guessed VCS (git, hg, etc.) repository.
Home-page: http://github.com/xliiv/pis
Author: xliiv
Author-email: tymoteusz.jankowski@gmail.com
License: MIT
Platform: UNKNOWN
Classifier: Programming Language :: Python
Classifier: Programming Language :: Python :: 3
